fastipc/__init__.py
fastipc/guarded_shared_memory.py
fastipc/utils.py
fastipc/_primitives/__init__.py
fastipc/_primitives/_primitives.c
fastipc/_primitives/_primitives.cpython-312-x86_64-linux-musl.so
fastipc/_primitives/_primitives.pyi
fastipc/data/__init__.py
fastipc/data/named_history_buffer.py
fastipc/data/named_queue.py
fastipc/nptree/__init__.py
fastipc/nptree/schema.py
fastipc/sync/__init__.py
fastipc/sync/named_event.py
fastipc/sync/named_mutex.py
fastipc/sync/named_semaphore.py
fastipc-0.1.5.dist-info/METADATA
fastipc-0.1.5.dist-info/WHEEL
fastipc-0.1.5.dist-info/top_level.txt
fastipc-0.1.5.dist-info/RECORD
fastipc-0.1.5.dist-info/licenses/LICENSE
