Metadata-Version: 2.4
Name: fastipc
Version: 0.1.5
Summary: Linux futex-based primitives (C extension)
Author-email: JihunLee <gkadnflh@gmail.com>
License-Expression: MIT
Project-URL: homepage, https://github.com/BlindedShooter/pyfastipc
Project-URL: repository, https://github.com/BlindedShooter/pyfastipc
Project-URL: Issues, https://github.com/BlindedShooter/pyfastipc/issues
Classifier: Programming Language :: Python :: 3
Classifier: Operating System :: POSIX :: Linux
Classifier: Programming Language :: C
Requires-Python: >=3.9
License-File: LICENSE
Requires-Dist: numpy>=2
Requires-Dist: optree>=0
Provides-Extra: test
Requires-Dist: pytest; extra == "test"
Requires-Dist: pytest-timeout; extra == "test"
Requires-Dist: pytest-benchmark; extra == "test"
Dynamic: license-file
Dynamic: requires-python
